rdfhash/__init__.py
rdfhash/cli.py
rdfhash/logger.py
rdfhash/main.py
rdfhash/utils/__init__.py
rdfhash/utils/graph.py
rdfhash/utils/hash.py
rdfhash-0.4.6.dist-info/LICENSE.txt
rdfhash-0.4.6.dist-info/METADATA
rdfhash-0.4.6.dist-info/WHEEL
rdfhash-0.4.6.dist-info/entry_points.txt
rdfhash-0.4.6.dist-info/top_level.txt
rdfhash-0.4.6.dist-info/RECORD
