Metadata-Version: 2.1
Name: rdfhash
Version: 0.4.6
Summary: De-duplicate RDF triples w/ a SPARQL query. Subjects taken from SELECT are replaced by the hash of their triples '{predicate} {object}. ' pairs sorted.
Home-page: https://github.com/NeilGraham/rdfhash
Author: Neil Graham
Author-email: grahamneiln@gmail.com
License: UNKNOWN
Platform: UNKNOWN
Requires-Python: >=3.7
Requires-Dist: pytest (>=7.1.2)
Requires-Dist: rdflib (>=6.1.1)
Requires-Dist: oxrdflib (>=0.3.4)
Requires-Dist: pyoxigraph (>=0.3.16)
